nktg_law/__init__.py
nktg_law-1.0.0.dist-info/METADATA
nktg_law-1.0.0.dist-info/WHEEL
nktg_law-1.0.0.dist-info/top_level.txt
nktg_law-1.0.0.dist-info/RECORD
