Metadata-Version: 2.4
Name: nktg-law
Version: 1.0.0
Summary: Python SDK for NKTg Law
Author: NKTgLaw
Requires-Python: >=3.7
Dynamic: author
Dynamic: requires-python
Dynamic: summary
